HttpLibrary/HttpLibrary.py
HttpLibrary/__init__.py
HttpLibrary/version.py
rf_httplibrary-4.0a4.dist-info/LICENSE
rf_httplibrary-4.0a4.dist-info/METADATA
rf_httplibrary-4.0a4.dist-info/WHEEL
rf_httplibrary-4.0a4.dist-info/top_level.txt
rf_httplibrary-4.0a4.dist-info/RECORD
