Metadata-Version: 2.1
Name: rf-httplibrary
Version: 4.0a4
Summary: HTTP Request Test Library.
Home-page: https://github.com/MainSystemDev/rf-httplibrary
Author: Shiela Buitizon
Author-email: shiela.buitizon@mnltechnology.com
License: license
Platform: any
Classifier: Development Status :: 4 - Beta
Classifier: License :: OSI Approved :: MIT License
Classifier: Operating System :: OS Independent
Classifier: Programming Language :: Python :: 3
Classifier: Topic :: Software Development :: Testing
Classifier: Framework :: Robot Framework
Classifier: Framework :: Robot Framework :: Library
License-File: LICENSE
Requires-Dist: jsonpath-rw-ext (>=0.1.9)
Requires-Dist: jsonpath-rw (==1.4.0)
Requires-Dist: jsonschema (==3.2.0)
Requires-Dist: requests
Requires-Dist: requests-toolbelt
Requires-Dist: robotframework (>=5.0.1)
